envelopes/__init__.py
envelopes/compat.py
envelopes/conn.py
envelopes/connstack.py
envelopes/envelope.py
envelopes/local.py
tctc_envelopes-0.5.dist-info/DESCRIPTION.rst
tctc_envelopes-0.5.dist-info/METADATA
tctc_envelopes-0.5.dist-info/RECORD
tctc_envelopes-0.5.dist-info/WHEEL
tctc_envelopes-0.5.dist-info/metadata.json
tctc_envelopes-0.5.dist-info/top_level.txt
