Metadata-Version: 2.0
Name: tctc-envelopes
Version: 0.5
Summary: Mailing for human beings
Home-page: http://tomekwojcik.github.io/envelopes/
Author: Tomasz Wójcik
Author-email: tomek@bthlabs.pl
License: https://github.com/tomekwojcik/envelopes/blob/master/LICENSE
Download-URL: http://github.com/tomekwojcik/envelopes/tarball/v0.5
Platform: any
Classifier: Development Status :: 4 - Beta
Classifier: Environment :: Other Environment
Classifier: Intended Audience :: Developers
Classifier: License :: OSI Approved :: MIT License
Classifier: Operating System :: OS Independent
Classifier: Programming Language :: Python :: 2
Classifier: Programming Language :: Python :: 2.6
Classifier: Programming Language :: Python :: 2.7
Classifier: Programming Language :: Python :: 3
Classifier: Programming Language :: Python :: 3.3
Classifier: Programming Language :: Python :: 3.4
Classifier: Programming Language :: Python :: 3.5
Classifier: Topic :: Software Development :: Libraries :: Python Modules
Provides-Extra: build
Requires-Dist: yapf; extra == 'build'
Requires-Dist: pyflakes; extra == 'build'
Requires-Dist: nose; extra == 'build'
Requires-Dist: unittest2; extra == 'build'
Provides-Extra: docs
Requires-Dist: sphinx; extra == 'docs'
